Workbook

Sheet Сверка цен
A1: № | B1: Позиция | C1: Ед. | D1: Смета: диапазон (Хаб.) | E1: Рынок мин | F1: Рынок макс | G1: Рынок средняя | H1: Отклонение средней от середины сметы | I1: Аренда/мес, средняя | J1: Смета: аренда/мес | K1: НДС | L1: Доставка / монтаж / подача | M1: Источники | N1: Дата | O1: Допущение? | P1: Вывод
A2: ТРАНСПОРТ И СПЕЦТЕХНИКА (аренда с оператором, смена 8 ч)
A3: 1 | B3: Бульдозер Т-130/Shantui SD16/D65 | C3: смена | D3: 12 000 - 18 000 ₽ | E3: 15200 | F3: 28000 | G3: 24000 | H3: 0.6 | I3: 420000 | J3: от 300 000 ₽ | K3: частники без НДС; buldozer-khabarovsk, Arena27 — с НДС | L3: трал отдельно 15–25 тыс./рейс | M3: perevozka24.com/habarovsk-27 (SD16 1900 ₽/ч, Т-170 3500 ₽/ч); stroitaxi.ru (от 2500 ₽/ч); exkavator.ru (D6R 2200 ₽/ч); farpost (от 2500 ₽/ч) | N3: 20.10.2026 | P3: Занижено: смена на 30–35%, месяц на 25–35%
A4: 2 | B4: Экскаватор гусеничный 0,5 м³ | C4: смена | D4: 16 000 - 22 000 ₽ | E4: 13600 | F4: 20000 | G4: 16000 | H4: -0.15789474 | I4: 310000 | J4: от 350 000 ₽ | K4: в осн. без НДС | L4: трал обязателен 10–17 тыс. | M4: uslugi.yandex.ru (PC-128 1700 ₽/ч); perevozka24 (SK100W 16 000/смена, EX100 16 000/смена); ecorex (от 1900 ₽/ч) | N4: 20.10.2026 | P4: Верх смены и месяц слегка завышены
A5: 3 | B5: Экскаватор-погрузчик JCB 3CX | C5: смена | D5: 18 000 - 23 000 ₽ | E5: 20000 | F5: 28000 | G5: 23000 | H5: 0.12195122 | I5: 440000 | J5: от 400 000 ₽ | K5: частники без НДС; есть с НДС 3500 ₽/ч | L5: своим ходом | M5: arena27.ru (2500 ₽/ч, мин 4 ч); uslugi.yandex.ru (от 36–40 тыс./день); farpost (2800–3500 ₽/ч) | N5: 20.10.2026 | P5: Смена в рынке, месяц занижен на 5–10%
A6: 4 | B6: Мини-погрузчик Bobcat S630 (аналоги S300/643) | C6: смена | D6: 12 000 - 16 000 ₽ | E6: 8000 | F6: 16000 | G6: 12000 | H6: -0.14285714 | I6: 240000 | J6: от 280 000 ₽ | K6: без НДС | L6: доставка ~4000 ₽ | M6: uslugi.yandex.ru (S300 от 1000, 643 от 1500 ₽/ч); perevozka24 (1000 ₽/ч; 13 000/смена) | N6: 20.10.2026 | O6: ДА | P6: Завышено: верх смены ~15%, месяц 10–30%
A7: 5 | B7: Самосвал КАМАЗ до 15 т | C7: смена | D7: 9 000 - 14 000 ₽ | E7: 12000 | F7: 22400 | G7: 17000 | H7: 0.47826087 | I7: 300000 | J7: от 280 000 ₽ | K7: без НДС; ДЭСК — юрлицо | L7: дорога ≥1 ч | M7: perevozka24 (1500–2000 ₽/ч); uslugi.yandex.ru (ДЭСК 2800 ₽/ч, мин 8 ч; Тонар от 1500) | N7: 20.10.2026 | P7: Занижено: смена на 20–40%
A8: 6 | B8: Манипулятор 5–7 т | C8: смена | D8: 18 000 - 25 000 ₽ | E8: 16000 | F8: 32000 | G8: 22000 | H8: 0.023255814 | I8: 400000 | J8: от 380 000 ₽ | K8: без НДС | L8: мин 2 ч | M8: perevozka24 (2000–3500 ₽/ч; 30–32 тыс./смена); uslugi.yandex.ru (1500–4500 ₽/ч) | N8: 20.10.2026 | P8: В рынке
A9: 7 | B9: Автовышка 18 м | C9: смена | D9: 18 000 - 24 000 ₽ | E9: 14000 | F9: 24000 | G9: 16500 | H9: -0.21428571 | I9: 320000 | J9: от 380 000 ₽ | K9: без НДС | L9: мин 3–4 ч с дорогой | M9: stroitaxi.ru (18 м от 1800 ₽/ч); perevozka24 (14–21 тыс./смена); uslugi.yandex.ru (от 1700 ₽/ч) | N9: 20.10.2026 | P9: Завышено: смена 10–25%, месяц 15–25%
A10: 8 | B10: Тягач + полуприцеп/трал | C10: смена | D10: 16 000 - 22 000 ₽ | E10: 14500 | F10: 25000 | G10: 18000 | H10: -0.052631579 | I10: 340000 | J10: от 280 000 ₽ | K10: без НДС | L10: межгород 50–200 ₽/км | M10: perevozka24 (14 500–25 000/смена); uslugi.yandex.ru (трал от 2400 ₽/ч); stroitaxi (от 10 000 за услугу) | N10: 20.10.2026 | O10: ДА | P10: Смена в рынке, месяц занижен 15–25%
A11: 9 | B11: Бортовой автомобиль до 5 т | C11: смена | D11: 7 000 - 10 000 ₽ | E11: 10400 | F11: 13600 | G11: 11600 | H11: 0.36470588 | I11: 220000 | J11: от 170 000 ₽ | K11: без НДС | L11: мин 2 ч | M11: perevozka24 (Hino 5 т 1300 ₽/ч); gruz27.ru (1700 ₽/ч); uslugi.yandex.ru (1350–1500 ₽/ч) | N11: 20.10.2026 | P11: Занижено: смена 15–30%, месяц 20–35%
A12: 10 | B12: Автокран 16 т (Ивановец) | C12: смена | D12: 20 000 - 28 000 ₽ | E12: 16000 | F12: 32000 | G12: 22500 | H12: -0.0625 | I12: 420000 | J12: от 400 000 ₽ | K12: без НДС | L12: мин 3–4 ч | M12: uslugi.yandex.ru (до 15 т от 2500 ₽/ч); farpost (от 3000 ₽/ч); perevozka24 (25 т 24 000/смена) | N12: 20.10.2026 | P12: В рынке
A13: 11 | B13: Компрессор дизельный ~5 м³/мин | C13: смена | D13: 6 000 - 10 000 ₽ | E13: 4000 | F13: 17600 | G13: 6500 | H13: -0.1875 | I13: 110000 | J13: от 130 000 ₽ | K13: прокаты — безнал с НДС | L13: буксир, доставка от 200 ₽ | M13: stroika-arenda (XAS 97 4000 ₽/сут); стахановец.рф (DACS-3 4000–5000); perevozka24 (900–2200 ₽/ч с оператором) | N13: 20.10.2026 | O13: ДА | P13: Смена в рынке, месяц слегка завышен
A14: 12 | B14: Отбойный молоток пневматический | C14: смена | D14: 1 200 - 2 000 ₽ | E14: 900 | F14: 2500 | G14: 1500 | H14: -0.0625 | I14: 35000 | J14: от 20 000 ₽ | K14: есть с НДС | L14: доставка от 300 ₽ | M14: arenda-dv.ru (МОП-3 от 900); стахановец.рф (2100–2500); stroika-arenda (эл. 700–1600) | N14: 20.10.2026 | P14: Смена в рынке; месяц в смете ЗАНИЖЕН (реально 30–40 тыс.)
A15: 13 | B15: Пост газосварки/резки (без газов) | C15: смена | D15: 1 800 - 3 000 ₽ | E15: 400 | F15: 900 | G15: 600 | H15: -0.75 | I15: 15000 | J15: от 30 000 ₽ | K15: безнал есть | L15: 150–300 ₽ | M15: stroika-arenda (ПГУ-10П от 600, резак 400); arenda-dv (900–1800 с баллонами) | N15: 20.10.2026 | P15: ЗАВЫШЕНО ~в 3 раза
A16: 14 | B16: Сварочный аппарат до 350 А | C16: смена | D16: 800 - 1 500 ₽ | E16: 500 | F16: 900 | G16: 700 | H16: -0.39130435 | I16: 17000 | J16: от 15 000 ₽ | K16: безнал есть | L16: 150–300 ₽ | M16: стахановец.рф (ARC 315 600–800); 2gis Прокат-сервис (700); stroika-arenda (от 500) | N16: 20.10.2026 | P16: В рынке / чуть выше
A17: 15 | B17: Каток грунтовый 16–20 т (30 т в Хабаровске нет) | C17: смена | D17: 14 000 - 20 000 ₽ | E17: 15200 | F17: 22400 | G17: 19000 | H17: 0.11764706 | I17: 370000 | J17: от 350 000 ₽ | K17: частники без НДС | L17: трал отдельно | M17: perevozka24 (SR16 1900–2500 ₽/ч, 20 т 2400–2800 ₽/ч); borg-pro.ru (18 т от 1900 ₽/ч) | N17: 20.10.2026 | O17: ДА | P17: В рынке (класс заменён)
A18: 16 | B18: Бункер 8–20 м³ (установка+вывоз) | C18: вывоз | D18: 4 000 - 9 000 ₽ | E18: 3200 | F18: 9500 | G18: 5500 | H18: -0.15384615 | I18: 55000 | J18: от 60 000 ₽ | K18: без НДС | L18: погрузка 1200–7000 ₽ отдельно | M18: perevozka24 (8 м³ 3600–9500, 20 м³ 7500, 27 м³ 7500–8500); myguru (8 м³ от 3200, 20 м³ от 5700) | N18: 20.10.2026 | P18: В рынке
A19: 17 | B19: Полигон — приём отходов | C19: т | D19: 600 - 1 800 ₽ | E19: 798 | F19: 1500 | G19: 1100 | H19: -0.083333333 | K19: тариф без НДС (798,41) | L19: через ПС «Северная» | M19: Постановление КЦТ Хаб. края 26.11.2025 №40/46 (АО «Спецавтохозяйство», 798,41 ₽/т на 2026); abak27.ru (от 1500 ₽/м³) | N19: 20.10.2026 | P19: Низ ниже тарифа, верх завышен; реально 800–1300
A20: РАСХОДНЫЕ МАТЕРИАЛЫ
A21: 18 | B21: Ацетилен 40 л — заправка/обмен | C21: баллон | D21: 5 000 - 7 500 ₽ | E21: 5500 | F21: 13010 | G21: 7000 | H21: 0.12 | K21: станция — НДС 5% вкл. | L21: не вкл. | M21: stgdv.ru прайс 18.02.2026 (5600–7620, Комсомольск); vdsdv.ru Хабаровск (13 010); bizorg (5500) | N21: 20.10.2026 | P21: В рынке как заправка. Покупка с баллоном = 26–45 тыс. (смета занижена в 4–6 раз)
A22: 19 | B22: Пропан-бутан 50 л — заправка | C22: баллон | D22: 2 000 - 2 800 ₽ | E22: 1450 | F22: 2900 | G22: 2400 | H22: 0 | K22: НДС вкл. | L22: у «Эко-Газ» включена | M22: vdsdv.ru (2260); stgdv.ru (2760); эко-газ.рф (2900 с доставкой) | N22: 20.10.2026 | P22: В рынке
A23: 20 | B23: Кислород 40 л (6 м³) — заправка | C23: баллон | D23: 900 - 1 500 ₽ | E23: 700 | F23: 1350 | G23: 900 | H23: -0.25 | K23: НДС вкл. | L23: не вкл. | M23: stgdv.ru (760–780); vdsdv.ru (1350); kislorod-servis (700) | N23: 20.10.2026 | P23: Верх 1500 слегка завышен
A24: 21 | B24: Бензин АИ-95 (АИ-98 = 88,72 ₽) | C24: л | D24: 73 - 88 ₽ | E24: 75.69 | F24: 78.25 | G24: 75.7 | H24: -0.059627329 | K24: розница, вкл. | L24: — | M24: fuelprice.ru/t-habarovsk, 17–20.10.2026 (ННК 75,69; Роснефть 75,75–75,80; АИ-98 88,72) | N24: 20.10.2026 | P24: Низ 73 ниже рынка
A25: 22 | B25: Масло 2Т | C25: л | D25: 460 - 850 ₽ | E25: 342 | F25: 800 | G25: 520 | H25: -0.20610687 | K25: вкл. | L25: — | M25: hatar.ru Хабаровск (430–680); lemanapro Хабаровск (342–650); skatpower (470) | N25: 20.10.2026 | P25: В рынке
A26: 23 | B26: Масло цепное | C26: л | D26: 1 000 - 1 500 ₽ | E26: 250 | F26: 700 | G26: 480 | H26: -0.616 | K26: вкл. | L26: — | M26: lemanapro.ru (231–700); vseinstrumenti (368–429); husq.ru (1290–1490 — бренд) | N26: 20.10.2026 | O26: ДА | P26: ЗАВЫШЕНО в 2–3 раза (если не фирменное)
A27: СТРОИТЕЛЬНЫЕ МАТЕРИАЛЫ
A28: 24 | B28: Песок строительный II кл. (с доставкой) | C28: м³ | D28: 500 - 1 300 ₽ | E28: 500 | F28: 1280 | G28: 900 | H28: 0 | K28: НДС не указан | L28: вкл. в 900 (Виноградовка) | M28: amurcement.ru (730–760 + доставка от 1000); песоквхабаровске.рф (500 самовывоз / 900 с дост.); perevozka24 | N28: 20.10.2026 | P28: В рынке
A29: 25 | B29: Щебень гранитный крупный (80-120 нет; между 40-70 и 100-200) | C29: м³ | D29: 2 000 - 4 100 ₽ | E29: 1891 | F29: 3000 | G29: 2600 | H29: -0.14754098 | K29: вкл. 22% | L29: самовывоз ~2100; доставка +500–900 | M29: Корфовский каменный карьер, прайс с 01.02.2026 (40-70 1891, 100-200 2318 с НДС) aokkk.ru | N29: 20.10.2026 | O29: ДА | P29: Верх 4100 — только при дальней доставке
A30: 26 | B30: Щебень 20-40 | C30: м³ | D30: 1 990 - 2 800 ₽ | E30: 1952 | F30: 2800 | G30: 2300 | H30: -0.039665971 | K30: вкл. 22% | L30: +600–900 ₽/м³ | M30: Корфовский карьер (1952 с НДС, 01.02.2026); regtorg | N30: 20.10.2026 | P30: В рынке
A31: 27 | B31: Грунт растительный (навал с доставкой) | C31: м³ | D31: 500 - 2 500 ₽ | E31: 600 | F31: 1300 | G31: 800 | H31: -0.46666667 | K31: н/д | L31: рейс 6500–9500 | M31: ekogrunt-khv.ru (от 650; биг-бэг 2500); regtorg (599–1300) | N31: 20.10.2026 | P31: Верх 2500 — только биг-бэги
A32: 28 | B32: Вода техническая (водовоз) | C32: м³ | D32: 400 - 700 ₽ | E32: 500 | F32: 700 | G32: 600 | H32: 0.090909091 | K32: н/д | L32: вкл. | M32: perevozka24 (500–700); uslugi.yandex.ru (от 1500/заказ) | N32: 20.10.2026 | P32: В рынке
A33: 29 | B33: Асфальтобетон горячий тип А/Б (ЩМА ~8 500–9 000) | C33: т | D33: 3 400 - 7 000 ₽ | E33: 6300 | F33: 9000 | G33: 7000 | H33: 0.34615385 | K33: вероятно вкл. | L33: самосвал 25 т — 14 000/рейс | M33: 2gis «Дорожно-строительные материалы», прайс 30.04.2025 (А/Б 6500–6700, ЩМА 8300); пересчёт на 2026 +4–8% | N33: 20.10.2026 | O33: ДА | P33: Низ 3400 ЗАНИЖЕН почти вдвое
A34: 30 | B34: Катанка 6,3–6,5 мм | C34: т | D34: 80 000 - 91 000 ₽ | E34: 72000 | F34: 82000 | G34: 77000 | H34: -0.099415205 | K34: с НДС | L34: склад в Хабаровске | M34: Металлсервис Хабаровск, прайс price_hab.xls 20.10.2026 (А1 Ø6 78 590; катанки нет) | N34: 20.10.2026 | O34: ДА | P34: Слегка завышено
A35: 31 | B35: Лес круглый хвойный ø14–24 | C35: м³ | D35: 10 000 - 15 000 ₽ | E35: 3500 | F35: 8500 | G35: 6000 | H35: -0.52 | K35: н/д | L35: +1000–2500 | M35: gde.ru Хабаровск (3500); woodresource (лиственница 8500); berfi (3150–3500) | N35: 20.10.2026 | P35: ЗАВЫШЕНО в 1,5–2 раза
A36: 32 | B36: Брусок обрезной хвоя 1–2 с. | C36: м³ | D36: 18 000 - 24 000 ₽ | E36: 10500 | F36: 28000 | G36: 22000 | H36: 0.047619048 | K36: ДОК: оба варианта | L36: по городу | M36: docandrey.ru Андреевский ДОК (22 000–23 400 без НДС); gde.ru (10 500 ест. влажн.) | N36: 20.10.2026 | P36: В рынке
A37: 33 | B37: Доска обрезная 25 мм | C37: м³ | D37: 16 000 - 22 000 ₽ | E37: 9500 | F37: 22800 | G37: 18000 | H37: -0.052631579 | K37: ДОК: оба варианта | L37: по городу | M37: docandrey.ru (18 000–19 000); gde.ru (9500–10 500) | N37: 20.10.2026 | P37: В рынке
A38: 34 | B38: Геотекстиль 300 г/м² | C38: м² | D38: 31 - 90 ₽ | E38: 36 | F38: 147 | G38: 90 | H38: 0.48760331 | K38: н/д | L38: склады в Хабаровске | M38: promzapas Хабаровск (79–147); asc-khv.ru (100); uik-rus (от 36, опт) | N38: 20.10.2026 | P38: Низ 31 занижен
A39: 35 | B39: Камень бутовый 150–500 мм | C39: т | D39: 5 900 - 6 500 ₽ | E39: 1500 | F39: 3500 | G39: 2500 | H39: -0.59677419 | K39: — | L39: +500–1000 ₽/т | M39: Хабаровских цен нет; Корфовский карьер (тел. 4212 49-22-32); regtorg (другие города 600–2500) | N39: 20.10.2026 | O39: ДА | P39: ЗАВЫШЕНО в 2–3 раза
A40: 36 | B40: Плёнка ПЭ 200 мкм (500 мкм ≈ 60–90) | C40: м² | D40: 50 - 100 ₽ | E40: 20 | F40: 37 | G40: 30 | H40: -0.6 | K40: с НДС | L40: в городе | M40: khv-fanera.ru прайс 25.09.2026 (30,7 ₽/м²); техрегион Владивосток (36,7) | N40: 20.10.2026 | P40: ЗАВЫШЕНО в 2–3 раза для 200 мкм
A41: 37 | B41: Связующее полиуретановое (с доставкой) | C41: кг | D41: 340 - 585 ₽ | E41: 265 | F41: 630 | G41: 460 | H41: -0.0054054054 | K41: с НДС | L41: ПЭК ~60 ₽/кг | M41: hab.gumbit.ru (300–500); russian-polymer.ru (340–420); + ПЭК 60,4 ₽/кг | N41: 20.10.2026 | O41: ДА | P41: В рынке
A42: 38 | B42: Пигменты для крошки (с доставкой) | C42: кг | D42: 250 - 450 ₽ | E42: 165 | F42: 295 | G42: 270 | H42: -0.22857143 | K42: с НДС | L42: +60 ₽/кг | M42: hab.gumbit.ru (172–250); darina.com.ru (190–240) | N42: 20.10.2026 | O42: ДА | P42: В рынке
A43: 39 | B43: Крошка резиновая чёрная (с доставкой) | C43: кг | D43: 21 - 35 ₽ | E43: 21 | F43: 115 | G43: 55 | H43: 0.96428571 | K43: с НДС | L43: ПЭК ~60 ₽/кг; ЖД 15–25 | M43: hab.gumbit.ru (41–58); ural-rti (34–52); местные НьюЭко/Бриз — цены по запросу | N43: 20.10.2026 | O43: ДА | P43: ЗАНИЖЕНО (21–35 — цена в центре без доставки)
A44: 40 | B44: Крошка EPDM цветная (с доставкой) | C44: кг | D44: 153 - 180 ₽ | E44: 145 | F44: 220 | G44: 200 | H44: 0.2012012 | K44: с НДС | L44: +25–60 ₽/кг | M44: hab.gumbit.ru (158–182); granulos (152); regtorg (145–185) | N44: 20.10.2026 | O44: ДА | P44: Занижено на 15–35% с доставкой
A45: 41 | B45: Бордюр БР 100.20.8 серый | C45: шт | D45: 350 - 600 ₽ | E45: 250 | F45: 490 | G45: 340 | H45: -0.28421053 | K45: н/д | L45: миксер/манипулятор | M45: beton27company.ru (250); brushatka-ru.com (340 серый / 590 цветной); pulscen (217–490) | N45: 20.10.2026 | P45: Завышено (600 — цветной)
A46: 42 | B46: Пескобетон М300 (аналог Мастер Гарц) 30 кг | C46: мешок | D46: 420 - 500 ₽ | E46: 350 | F46: 500 | G46: 450 | H46: -0.02173913 | K46: розница | L46: самовывоз | M46: shop.stromix.ru (Старатели/RB, пересчёт на 30 кг); Мастер Гарц в Хабаровске нет | N46: 20.10.2026 | O46: ДА | P46: В рынке
A47: 43 | B47: Профнастил С8 0,45 RAL 6005, лист 1,2×2 | C47: лист | D47: 1 050 - 1 500 ₽ | E47: 1080 | F47: 1500 | G47: 1250 | H47: -0.019607843 | K47: н/д | L47: не вкл. | M47: profil-dv.ru (449 ₽/м² → 1078); профнастил-дв.рф (1160); metallprofil Хабаровск (≈1495) | N47: 20.10.2026 | P47: В рынке
A48: 44 | B48: Бетон М300 с доставкой (М400 ≈ 8 630) | C48: м³ | D48: 5 900 - 7 800 ₽ | E48: 7950 | F48: 9300 | G48: 8300 | H48: 0.21167883 | K48: ДБС с НДС, прочие н/д | L48: +1000–1200 ₽/м³ | M48: beton27khv.ru (6800/8000); beton27company.ru (6750/7950); beton-habarovsk.ru (7050); beton-khabarovsk.ru (9300) | N48: 20.10.2026 | P48: Низ 5900 занижен; М400 верх занижен
A49: 44а | B49: Автобетононасос (в смете отсутствует) | C49: час | D49: — (нет в смете) | E49: 2500 | F49: 7500 | G49: 6000 | K49: безнал с НДС | L49: мин 4–6 ч | M49: beton-habarovsk.ru (5200–7500); perevozka24 (1500–7000) | N49: 20.10.2026 | P49: НЕТ В СМЕТЕ — добавить
A50: 45 | B50: Поликарбонат сотовый 8 мм 2,1×6 (6 мм ≈5900, 10 мм ≈8900) | C50: лист | D50: 4 200 - 13 500 ₽ | E50: 4590 | F50: 10044 | G50: 7200 | H50: -0.18644068 | K50: ck.ru с НДС | L50: по городу | M50: ck.ru; profil-dv.ru; цос.рф; mega27.ru | N50: 20.10.2026 | P50: Верх 13 500 завышен
A51: 46 | B51: Брусчатка гранитная пиленая 200×100×60 | C51: м² | D51: 4 500 - 6 500 ₽ | E51: 4000 | F51: 8500 | G51: 5500 | H51: 0 | K51: н/д | L51: в Хабаровск +1000–1600 (допущение) | M51: granite-bruschatka.ru (Хабаровск, от 2400 / 50 мм); rok.ooo; russiangranit.ru (6500–8500); колотая местная stone-dv.ru 2300–3400 | N51: 20.10.2026 | O51: ДА | P51: В рынке без доставки; 60 мм в наличии в Хабаровске нет
A52: 47 | B52: Труба ПНД гофра ø50 двустенная с зондом | C52: м | D52: 100 - 180 ₽ | E52: 90 | F52: 151 | G52: 130 | H52: -0.071428571 | K52: н/д | L52: по городу | M52: khv.energosf.ru (EKF 90, IEK 135–151, DKC 139); tinko (146) | N52: 20.10.2026 | P52: В рынке (лёгкая 54 — не для грунта)
A53: 48 | B53: Кабель ВВГнг(А)-LS 5×2,5 | C53: м | D53: 290 - 380 ₽ | E53: 149 | F53: 300 | G53: 200 | H53: -0.40298507 | K53: н/д | L53: бесплатно от суммы | M53: электротовары-дв.рф (149/298); khv.energosf.ru (154–172); rs24 (168–222); etm (174) | N53: 20.10.2026 | P53: ЗАВЫШЕНО ~в 1,5 раза
A54: 49 | B54: Кабель ВВГнг(А)-LS 5×4 | C54: м | D54: 400 - 520 ₽ | E54: 310 | F54: 395 | G54: 370 | H54: -0.19565217 | K54: н/д | L54: — | M54: khv.energosf.ru (368–394); rs24 (387); e-kc.ru (391–395) | N54: 20.10.2026 | P54: Завышено на 15–25%
A55: 50 | B55: Кабель ВВГнг(А)-LS 5×16 (наружка: ВБШв ~1050–1760, АВБШв 256–298) | C55: м | D55: 950 - 1 200 ₽ | E55: 970 | F55: 1503 | G55: 1430 | H55: 0.33023256 | K55: н/д | L55: — | M55: khv.energosf.ru (1428); rs24 (969–1174); e-kc.ru (1493–1503); virage24 (1291–1391) | N55: 20.10.2026 | P55: ЗАНИЖЕНО (реально 1400–1500)
A56: ЛОГИСТИКА МОСКВА → ХАБАРОВСК
A57: 51 | B57: Фура 20 т (тент 82–96 м³), отдельная машина | C57: рейс | D57: - | E57: 593568 | F57: 962200 | G57: 780000 | K57: Балтрейлер без НДС 788 690 | L57: 10–14 сут | M57: baltrail.ru (788 690 без НДС, тариф 01.08.2026); rustransit77 (593 568); ПЭК сборный 60,4 ₽/кг (20 т ≈1,21 млн) | N57: 20.10.2026 | P57: В смете цены не было
A58: 52 | B58: ЖД-контейнер 40 фут дверь-дверь (20 фут ≈ 225 тыс., до 18 т) | C58: конт. | D58: - | E58: 215000 | F58: 300850 | G58: 300850 | K58: с НДС 22% (Contoperator) | L58: 25–30 сут | M58: contoperator.ru прайс с 01.07.2026 (20 фут 224 950; 40 фут 300 850 с НДС); tablogix (190 000 без НДС); rzdu.ru (от 198 000) | N58: 20.10.2026 | P58: В смете цены не было
A59: ПЕРСОНАЛ (₽/мес «на руки», город; работодателю ×1,50)
A60: 53 | B60: Разнорабочий (благоустройство) | C60: чел·мес | D60: 85 000 - 150 000 ₽ | E60: 75000 | F60: 120000 | G60: 90000 | H60: -0.23404255 | K60: на руки | L60: — | M60: hh.ru area=102, 20.10.2026 (130 вак.); trudvsem.ru (22 вак., 50–100 до вычета) | N60: 20.10.2026 | P60: Верх 150 — вахта
A61: 54 | B61: Водитель кат. C, E | C61: чел·мес | D61: 115 000 - 250 000 ₽ | E61: 110000 | F61: 230000 | G61: 160000 | H61: -0.12328767 | K61: на руки | L61: — | M61: hh.ru (13 вак.); trudvsem (47–120 до вычета) | N61: 20.10.2026 | P61: В рынке
A62: 55 | B62: Тракторист/машинист | C62: чел·мес | D62: 100 000 - 250 000 ₽ | E62: 110000 | F62: 150000 | G62: 120000 | H62: -0.31428571 | K62: на руки | L62: — | M62: hh.ru (187, в т.ч. вахты 210–280); trudvsem | N62: 20.10.2026 | P62: Верх 250 — вахта
A63: 56 | B63: Сварщик | C63: чел·мес | D63: 150 000 - 310 000 ₽ | E63: 70000 | F63: 150000 | G63: 120000 | H63: -0.47826087 | K63: на руки | L63: — | M63: hh.ru (123 вак.); trudvsem (город 50–140 до вычета) | N63: 20.10.2026 | P63: ЗАВЫШЕНО для города (310 — вахта+НАКС)
A64: 57 | B64: Строитель/укладчик плитки и бордюра | C64: чел·мес | D64: 100 000 - 180 000 ₽ | E64: 100000 | F64: 160000 | G64: 125000 | H64: -0.10714286 | K64: на руки | L64: — | M64: hh.ru (5–40 вак., мало данных) | N64: 20.10.2026 | O64: ДА | P64: В рынке
A65: 58 | B65: Начальник участка/прораб | C65: чел·мес | D65: 180 000 - 300 000 ₽ | E65: 100000 | F65: 210000 | G65: 140000 | H65: -0.41666667 | K65: на руки | L65: — | M65: hh.ru (69–82 вак.); trudvsem (100–120) | N65: 20.10.2026 | P65: ЗАВЫШЕНО для города
A66: 59 | B66: Кладовщик | C66: чел·мес | D66: 80 000 - 120 000 ₽ | E66: 65000 | F66: 160000 | G66: 100000 | H66: 0 | K66: на руки | L66: — | M66: hh.ru (327); trudvsem (80, медиана 54–65 до вычета) | N66: 20.10.2026 | P66: В рынке
A67: 60 | B67: Электрик (сети до 0,4 кВ) | C67: чел·мес | D67: 110 000 - 180 000 ₽ | E67: 60000 | F67: 165000 | G67: 105000 | H67: -0.27586207 | K67: на руки | L67: — | M67: hh.ru (275); trudvsem (173) | N67: 20.10.2026 | P67: Слегка завышено
A68: 61 | B68: Монтажник конструкций | C68: чел·мес | D68: 100 000 - 160 000 ₽ | E68: 100000 | F68: 150000 | G68: 120000 | H68: -0.076923077 | K68: на руки | L68: — | M68: hh.ru (34); trudvsem (36) | N68: 20.10.2026 | P68: В рынке
A69: 62 | B69: Бетонщик | C69: чел·мес | D69: 100 000 - 150 000 ₽ | E69: 100000 | F69: 120000 | G69: 110000 | H69: -0.12 | K69: на руки | L69: — | M69: hh.ru (26, из них 16 вахта) | N69: 20.10.2026 | P69: В рынке
A70: 63 | B70: Штукатур-маляр (фасады) | C70: чел·мес | D70: 80 000 - 150 000 ₽ | E70: 55000 | F70: 150000 | G70: 95000 | H70: -0.17391304 | K70: на руки | L70: — | M70: hh.ru (22); trudvsem (17) | N70: 20.10.2026 | P70: В рынке
A71: АРЕНДА ЖИЛЬЯ И ОФИСОВ
A72: 64 | B72: Квартира 1-комн., центр | C72: мес | D72: 35 000 - 65 000 ₽ | E72: 33000 | F72: 72000 | G72: 47000 | H72: -0.06 | K72: физлица без НДС | L72: комиссия 50–60% + залог 15–20 тыс., КУ 3–6 тыс. | M72: realty.yandex.ru Центральный р-н (19 объявл.); mirkvartir (807 объявл., ср. 41 213); cian (24 объявл., от 32,7 тыс.) | N72: 20.10.2026 | P72: В рынке; верх чуть занижен
A73: 65 | B73: Офис ~20 м², центр (≈1350 ₽/м²) | C73: мес | D73: 20 000 - 30 000 ₽ | E73: 14400 | F73: 49900 | G73: 27000 | H73: 0.08 | K73: не указан | L73: КУ сверху | M73: realty.yandex.ru (20 из 23 объявл.; Центр 69 объявл. 1000–2100 ₽/м²); mirkvartir | N73: 20.10.2026 | P73: В рынке
A74: 66 | B74: Хостел, койко-место | C74: сутки | D74: 1 500 - 3 000 ₽ | E74: 1200 | F74: 1800 | G74: 1500 | H74: -0.33333333 | K74: вкл. | L74: — | M74: habarovsk.sutochno.ru (12 койко-мест 1200–1800); 101hotels; ostrovok | N74: 20.10.2026 | P74: Верх 3000 ЗАВЫШЕН
A75: 66а | B75: Рабочее общежитие (в смете нет) | C75: чел·мес | D75: — (нет в смете) | E75: 9000 | F75: 15000 | G75: 12000 | K75: с НДС | L75: КУ вкл. | M75: hoster27.ru «Хостер», ул. Суворова 82А (300–500 ₽/сут) | N75: 20.10.2026 | P75: Добавить как основной вариант
A76: 67 | B76: Гостиница 3*, стандарт | C76: сутки | D76: 2 500 - 5 000 ₽ | E76: 2200 | F76: 7300 | G76: 4500 | H76: 0.2 | K76: обычно вкл. | L76: завтрак не всегда | M76: putevka.com (22 отеля, медиана 4174); 101hotels (19, медиана 4700); ostrovok (от 3800) | N76: 20.10.2026 | P76: Верх 5000 занижен

Sheet Сценарий бульвара
A1: № | B1: Позиция | C1: Ед. | D1: Кол-во (ДОПУЩЕНИЕ — замените своим) | E1: Основание объёма | F1: Цена ед., средняя | G1: Множитель (работодатель ×1,5) | H1: Сумма, ₽ | I1: Сумма по мин., ₽ | J1: Сумма по макс., ₽
A2: ТРАНСПОРТ И СПЕЦТЕХНИКА (аренда с оператором, смена 8 ч)
A3: 1 | B3: Бульдозер Т-130/Shantui SD16/D65 | C3: смена | D3: 15 | E3: планировка, срезка | F3: ='Сверка цен'!G3 | G3: 1 | H3: =D3*F3*G3 | I3: =D3*'Сверка цен'!E3*G3 | J3: =D3*'Сверка цен'!F3*G3
A4: 2 | B4: Экскаватор гусеничный 0,5 м³ | C4: смена | D4: 30 | E4: котлованы, траншеи | F4: ='Сверка цен'!G4 | G4: 1 | H4: =D4*F4*G4 | I4: =D4*'Сверка цен'!E4*G4 | J4: =D4*'Сверка цен'!F4*G4
A5: 3 | B5: Экскаватор-погрузчик JCB 3CX | C5: смена | D5: 60 | E5: универсальная машина | F5: ='Сверка цен'!G5 | G5: 1 | H5: =D5*F5*G5 | I5: =D5*'Сверка цен'!E5*G5 | J5: =D5*'Сверка цен'!F5*G5
A6: 4 | B6: Мини-погрузчик Bobcat S630 (аналоги S300/643) | C6: смена | D6: 60 | E6: планировка, подача | F6: ='Сверка цен'!G6 | G6: 1 | H6: =D6*F6*G6 | I6: =D6*'Сверка цен'!E6*G6 | J6: =D6*'Сверка цен'!F6*G6
A7: 5 | B7: Самосвал КАМАЗ до 15 т | C7: смена | D7: 120 | E7: 2 машины × 60 смен | F7: ='Сверка цен'!G7 | G7: 1 | H7: =D7*F7*G7 | I7: =D7*'Сверка цен'!E7*G7 | J7: =D7*'Сверка цен'!F7*G7
A8: 6 | B8: Манипулятор 5–7 т | C8: смена | D8: 20 | E8: бордюр, опоры | F8: ='Сверка цен'!G8 | G8: 1 | H8: =D8*F8*G8 | I8: =D8*'Сверка цен'!E8*G8 | J8: =D8*'Сверка цен'!F8*G8
A9: 7 | B9: Автовышка 18 м | C9: смена | D9: 15 | E9: монтаж светильников | F9: ='Сверка цен'!G9 | G9: 1 | H9: =D9*F9*G9 | I9: =D9*'Сверка цен'!E9*G9 | J9: =D9*'Сверка цен'!F9*G9
A10: 8 | B10: Тягач + полуприцеп/трал | C10: смена | D10: 6 | E10: перебазировка техники | F10: ='Сверка цен'!G10 | G10: 1 | H10: =D10*F10*G10 | I10: =D10*'Сверка цен'!E10*G10 | J10: =D10*'Сверка цен'!F10*G10
A11: 9 | B11: Бортовой автомобиль до 5 т | C11: смена | D11: 40 | F11: ='Сверка цен'!G11 | G11: 1 | H11: =D11*F11*G11 | I11: =D11*'Сверка цен'!E11*G11 | J11: =D11*'Сверка цен'!F11*G11
A12: 10 | B12: Автокран 16 т (Ивановец) | C12: смена | D12: 15 | F12: ='Сверка цен'!G12 | G12: 1 | H12: =D12*F12*G12 | I12: =D12*'Сверка цен'!E12*G12 | J12: =D12*'Сверка цен'!F12*G12
A13: 11 | B13: Компрессор дизельный ~5 м³/мин | C13: смена | D13: 20 | E13: демонтаж | F13: ='Сверка цен'!G13 | G13: 1 | H13: =D13*F13*G13 | I13: =D13*'Сверка цен'!E13*G13 | J13: =D13*'Сверка цен'!F13*G13
A14: 12 | B14: Отбойный молоток пневматический | C14: смена | D14: 20 | F14: ='Сверка цен'!G14 | G14: 1 | H14: =D14*F14*G14 | I14: =D14*'Сверка цен'!E14*G14 | J14: =D14*'Сверка цен'!F14*G14
A15: 13 | B15: Пост газосварки/резки (без газов) | C15: смена | D15: 10 | F15: ='Сверка цен'!G15 | G15: 1 | H15: =D15*F15*G15 | I15: =D15*'Сверка цен'!E15*G15 | J15: =D15*'Сверка цен'!F15*G15
A16: 14 | B16: Сварочный аппарат до 350 А | C16: смена | D16: 30 | F16: ='Сверка цен'!G16 | G16: 1 | H16: =D16*F16*G16 | I16: =D16*'Сверка цен'!E16*G16 | J16: =D16*'Сверка цен'!F16*G16
A17: 15 | B17: Каток грунтовый 16–20 т (30 т в Хабаровске нет) | C17: смена | D17: 25 | F17: ='Сверка цен'!G17 | G17: 1 | H17: =D17*F17*G17 | I17: =D17*'Сверка цен'!E17*G17 | J17: =D17*'Сверка цен'!F17*G17
A18: 16 | B18: Бункер 8–20 м³ (установка+вывоз) | C18: вывоз | D18: 30 | F18: ='Сверка цен'!G18 | G18: 1 | H18: =D18*F18*G18 | I18: =D18*'Сверка цен'!E18*G18 | J18: =D18*'Сверка цен'!F18*G18
A19: 17 | B19: Полигон — приём отходов | C19: т | D19: 300 | E19: демонтаж старых покрытий | F19: ='Сверка цен'!G19 | G19: 1 | H19: =D19*F19*G19 | I19: =D19*'Сверка цен'!E19*G19 | J19: =D19*'Сверка цен'!F19*G19
A20: РАСХОДНЫЕ МАТЕРИАЛЫ
A21: 18 | B21: Ацетилен 40 л — заправка/обмен | C21: баллон | D21: 10 | F21: ='Сверка цен'!G21 | G21: 1 | H21: =D21*F21*G21 | I21: =D21*'Сверка цен'!E21*G21 | J21: =D21*'Сверка цен'!F21*G21
A22: 19 | B22: Пропан-бутан 50 л — заправка | C22: баллон | D22: 15 | F22: ='Сверка цен'!G22 | G22: 1 | H22: =D22*F22*G22 | I22: =D22*'Сверка цен'!E22*G22 | J22: =D22*'Сверка цен'!F22*G22
A23: 20 | B23: Кислород 40 л (6 м³) — заправка | C23: баллон | D23: 30 | F23: ='Сверка цен'!G23 | G23: 1 | H23: =D23*F23*G23 | I23: =D23*'Сверка цен'!E23*G23 | J23: =D23*'Сверка цен'!F23*G23
A24: 21 | B24: Бензин АИ-95 (АИ-98 = 88,72 ₽) | C24: л | D24: 2000 | F24: ='Сверка цен'!G24 | G24: 1 | H24: =D24*F24*G24 | I24: =D24*'Сверка цен'!E24*G24 | J24: =D24*'Сверка цен'!F24*G24
A25: 22 | B25: Масло 2Т | C25: л | D25: 40 | F25: ='Сверка цен'!G25 | G25: 1 | H25: =D25*F25*G25 | I25: =D25*'Сверка цен'!E25*G25 | J25: =D25*'Сверка цен'!F25*G25
A26: 23 | B26: Масло цепное | C26: л | D26: 20 | F26: ='Сверка цен'!G26 | G26: 1 | H26: =D26*F26*G26 | I26: =D26*'Сверка цен'!E26*G26 | J26: =D26*'Сверка цен'!F26*G26
A27: СТРОИТЕЛЬНЫЕ МАТЕРИАЛЫ
A28: 24 | B28: Песок строительный II кл. (с доставкой) | C28: м³ | D28: 650 | E28: основания 4100 м² × 0,15 | F28: ='Сверка цен'!G28 | G28: 1 | H28: =D28*F28*G28 | I28: =D28*'Сверка цен'!E28*G28 | J28: =D28*'Сверка цен'!F28*G28
A29: 25 | B29: Щебень гранитный крупный (80-120 нет; между 40-70 и 100-200) | C29: м³ | D29: 200 | E29: нижний слой основания | F29: ='Сверка цен'!G29 | G29: 1 | H29: =D29*F29*G29 | I29: =D29*'Сверка цен'!E29*G29 | J29: =D29*'Сверка цен'!F29*G29
A30: 26 | B30: Щебень 20-40 | C30: м³ | D30: 650 | E30: основания 4100 м² × 0,15 | F30: ='Сверка цен'!G30 | G30: 1 | H30: =D30*F30*G30 | I30: =D30*'Сверка цен'!E30*G30 | J30: =D30*'Сверка цен'!F30*G30
A31: 27 | B31: Грунт растительный (навал с доставкой) | C31: м³ | D31: 750 | E31: газон 5000 м² × 0,15 | F31: ='Сверка цен'!G31 | G31: 1 | H31: =D31*F31*G31 | I31: =D31*'Сверка цен'!E31*G31 | J31: =D31*'Сверка цен'!F31*G31
A32: 28 | B32: Вода техническая (водовоз) | C32: м³ | D32: 200 | F32: ='Сверка цен'!G32 | G32: 1 | H32: =D32*F32*G32 | I32: =D32*'Сверка цен'!E32*G32 | J32: =D32*'Сверка цен'!F32*G32
A33: 29 | B33: Асфальтобетон горячий тип А/Б (ЩМА ~8 500–9 000) | C33: т | D33: 120 | E33: 1000 м² × 5 см | F33: ='Сверка цен'!G33 | G33: 1 | H33: =D33*F33*G33 | I33: =D33*'Сверка цен'!E33*G33 | J33: =D33*'Сверка цен'!F33*G33
A34: 30 | B34: Катанка 6,3–6,5 мм | C34: т | D34: 2 | F34: ='Сверка цен'!G34 | G34: 1 | H34: =D34*F34*G34 | I34: =D34*'Сверка цен'!E34*G34 | J34: =D34*'Сверка цен'!F34*G34
A35: 31 | B35: Лес круглый хвойный ø14–24 | C35: м³ | D35: 10 | F35: ='Сверка цен'!G35 | G35: 1 | H35: =D35*F35*G35 | I35: =D35*'Сверка цен'!E35*G35 | J35: =D35*'Сверка цен'!F35*G35
A36: 32 | B36: Брусок обрезной хвоя 1–2 с. | C36: м³ | D36: 5 | F36: ='Сверка цен'!G36 | G36: 1 | H36: =D36*F36*G36 | I36: =D36*'Сверка цен'!E36*G36 | J36: =D36*'Сверка цен'!F36*G36
A37: 33 | B37: Доска обрезная 25 мм | C37: м³ | D37: 10 | E37: опалубка | F37: ='Сверка цен'!G37 | G37: 1 | H37: =D37*F37*G37 | I37: =D37*'Сверка цен'!E37*G37 | J37: =D37*'Сверка цен'!F37*G37
A38: 34 | B38: Геотекстиль 300 г/м² | C38: м² | D38: 4500 | F38: ='Сверка цен'!G38 | G38: 1 | H38: =D38*F38*G38 | I38: =D38*'Сверка цен'!E38*G38 | J38: =D38*'Сверка цен'!F38*G38
A39: 35 | B39: Камень бутовый 150–500 мм | C39: т | D39: 50 | F39: ='Сверка цен'!G39 | G39: 1 | H39: =D39*F39*G39 | I39: =D39*'Сверка цен'!E39*G39 | J39: =D39*'Сверка цен'!F39*G39
A40: 36 | B40: Плёнка ПЭ 200 мкм (500 мкм ≈ 60–90) | C40: м² | D40: 1000 | F40: ='Сверка цен'!G40 | G40: 1 | H40: =D40*F40*G40 | I40: =D40*'Сверка цен'!E40*G40 | J40: =D40*'Сверка цен'!F40*G40
A41: 37 | B41: Связующее полиуретановое (с доставкой) | C41: кг | D41: 1100 | E41: резин. покрытие 600 м² | F41: ='Сверка цен'!G41 | G41: 1 | H41: =D41*F41*G41 | I41: =D41*'Сверка цен'!E41*G41 | J41: =D41*'Сверка цен'!F41*G41
A42: 38 | B42: Пигменты для крошки (с доставкой) | C42: кг | D42: 100 | F42: ='Сверка цен'!G42 | G42: 1 | H42: =D42*F42*G42 | I42: =D42*'Сверка цен'!E42*G42 | J42: =D42*'Сверка цен'!F42*G42
A43: 39 | B43: Крошка резиновая чёрная (с доставкой) | C43: кг | D43: 4200 | E43: 7 кг/м² | F43: ='Сверка цен'!G43 | G43: 1 | H43: =D43*F43*G43 | I43: =D43*'Сверка цен'!E43*G43 | J43: =D43*'Сверка цен'!F43*G43
A44: 40 | B44: Крошка EPDM цветная (с доставкой) | C44: кг | D44: 3000 | E44: 5 кг/м² | F44: ='Сверка цен'!G44 | G44: 1 | H44: =D44*F44*G44 | I44: =D44*'Сверка цен'!E44*G44 | J44: =D44*'Сверка цен'!F44*G44
A45: 41 | B45: Бордюр БР 100.20.8 серый | C45: шт | D45: 2000 | F45: ='Сверка цен'!G45 | G45: 1 | H45: =D45*F45*G45 | I45: =D45*'Сверка цен'!E45*G45 | J45: =D45*'Сверка цен'!F45*G45
A46: 42 | B46: Пескобетон М300 (аналог Мастер Гарц) 30 кг | C46: мешок | D46: 200 | F46: ='Сверка цен'!G46 | G46: 1 | H46: =D46*F46*G46 | I46: =D46*'Сверка цен'!E46*G46 | J46: =D46*'Сверка цен'!F46*G46
A47: 43 | B47: Профнастил С8 0,45 RAL 6005, лист 1,2×2 | C47: лист | D47: 420 | E47: врем. ограждение 500 м | F47: ='Сверка цен'!G47 | G47: 1 | H47: =D47*F47*G47 | I47: =D47*'Сверка цен'!E47*G47 | J47: =D47*'Сверка цен'!F47*G47
A48: 44 | B48: Бетон М300 с доставкой (М400 ≈ 8 630) | C48: м³ | D48: 80 | E48: фундаменты опор, МАФ | F48: ='Сверка цен'!G48 | G48: 1 | H48: =D48*F48*G48 | I48: =D48*'Сверка цен'!E48*G48 | J48: =D48*'Сверка цен'!F48*G48
A49: 44а | B49: Автобетононасос (в смете отсутствует) | C49: час | D49: 16 | E49: 4 выезда × 4 ч | F49: ='Сверка цен'!G49 | G49: 1 | H49: =D49*F49*G49 | I49: =D49*'Сверка цен'!E49*G49 | J49: =D49*'Сверка цен'!F49*G49
A50: 45 | B50: Поликарбонат сотовый 8 мм 2,1×6 (6 мм ≈5900, 10 мм ≈8900) | C50: лист | D50: 20 | E50: навесы | F50: ='Сверка цен'!G50 | G50: 1 | H50: =D50*F50*G50 | I50: =D50*'Сверка цен'!E50*G50 | J50: =D50*'Сверка цен'!F50*G50
A51: 46 | B51: Брусчатка гранитная пиленая 200×100×60 | C51: м² | D51: 2500 | E51: основные дорожки | F51: ='Сверка цен'!G51 | G51: 1 | H51: =D51*F51*G51 | I51: =D51*'Сверка цен'!E51*G51 | J51: =D51*'Сверка цен'!F51*G51
A52: 47 | B52: Труба ПНД гофра ø50 двустенная с зондом | C52: м | D52: 1500 | F52: ='Сверка цен'!G52 | G52: 1 | H52: =D52*F52*G52 | I52: =D52*'Сверка цен'!E52*G52 | J52: =D52*'Сверка цен'!F52*G52
A53: 48 | B53: Кабель ВВГнг(А)-LS 5×2,5 | C53: м | D53: 300 | F53: ='Сверка цен'!G53 | G53: 1 | H53: =D53*F53*G53 | I53: =D53*'Сверка цен'!E53*G53 | J53: =D53*'Сверка цен'!F53*G53
A54: 49 | B54: Кабель ВВГнг(А)-LS 5×4 | C54: м | D54: 500 | F54: ='Сверка цен'!G54 | G54: 1 | H54: =D54*F54*G54 | I54: =D54*'Сверка цен'!E54*G54 | J54: =D54*'Сверка цен'!F54*G54
A55: 50 | B55: Кабель ВВГнг(А)-LS 5×16 (наружка: ВБШв ~1050–1760, АВБШв 256–298) | C55: м | D55: 1000 | E55: сеть освещения | F55: ='Сверка цен'!G55 | G55: 1 | H55: =D55*F55*G55 | I55: =D55*'Сверка цен'!E55*G55 | J55: =D55*'Сверка цен'!F55*G55
A56: ЛОГИСТИКА МОСКВА → ХАБАРОВСК
A57: 51 | B57: Фура 20 т (тент 82–96 м³), отдельная машина | C57: рейс | D57: 0 | E57: не нужна, если всё берётся в Хабаровске | F57: ='Сверка цен'!G57 | G57: 1 | H57: =D57*F57*G57 | I57: =D57*'Сверка цен'!E57*G57 | J57: =D57*'Сверка цен'!F57*G57
A58: 52 | B58: ЖД-контейнер 40 фут дверь-дверь (20 фут ≈ 225 тыс., до 18 т) | C58: конт. | D58: 13 | E58: брусчатка 2500 м² × 135 кг = 337 т | F58: ='Сверка цен'!G58 | G58: 1 | H58: =D58*F58*G58 | I58: =D58*'Сверка цен'!E58*G58 | J58: =D58*'Сверка цен'!F58*G58
A59: ПЕРСОНАЛ (₽/мес «на руки», город; работодателю ×1,50)
A60: 53 | B60: Разнорабочий (благоустройство) | C60: чел·мес | D60: 32 | E60: 8 чел × 4 мес | F60: ='Сверка цен'!G60 | G60: 1.5 | H60: =D60*F60*G60 | I60: =D60*'Сверка цен'!E60*G60 | J60: =D60*'Сверка цен'!F60*G60
A61: 54 | B61: Водитель кат. C, E | C61: чел·мес | D61: 8 | E61: 2 × 4 (техника в аренде — с водителем) | F61: ='Сверка цен'!G61 | G61: 1.5 | H61: =D61*F61*G61 | I61: =D61*'Сверка цен'!E61*G61 | J61: =D61*'Сверка цен'!F61*G61
A62: 55 | B62: Тракторист/машинист | C62: чел·мес | D62: 4 | E62: 1 × 4 | F62: ='Сверка цен'!G62 | G62: 1.5 | H62: =D62*F62*G62 | I62: =D62*'Сверка цен'!E62*G62 | J62: =D62*'Сверка цен'!F62*G62
A63: 56 | B63: Сварщик | C63: чел·мес | D63: 4 | E63: 1 × 4 | F63: ='Сверка цен'!G63 | G63: 1.5 | H63: =D63*F63*G63 | I63: =D63*'Сверка цен'!E63*G63 | J63: =D63*'Сверка цен'!F63*G63
A64: 57 | B64: Строитель/укладчик плитки и бордюра | C64: чел·мес | D64: 24 | E64: 6 × 4 | F64: ='Сверка цен'!G64 | G64: 1.5 | H64: =D64*F64*G64 | I64: =D64*'Сверка цен'!E64*G64 | J64: =D64*'Сверка цен'!F64*G64
A65: 58 | B65: Начальник участка/прораб | C65: чел·мес | D65: 4 | E65: 1 × 4 | F65: ='Сверка цен'!G65 | G65: 1.5 | H65: =D65*F65*G65 | I65: =D65*'Сверка цен'!E65*G65 | J65: =D65*'Сверка цен'!F65*G65
A66: 59 | B66: Кладовщик | C66: чел·мес | D66: 4 | E66: 1 × 4 | F66: ='Сверка цен'!G66 | G66: 1.5 | H66: =D66*F66*G66 | I66: =D66*'Сверка цен'!E66*G66 | J66: =D66*'Сверка цен'!F66*G66
A67: 60 | B67: Электрик (сети до 0,4 кВ) | C67: чел·мес | D67: 8 | E67: 2 × 4 | F67: ='Сверка цен'!G67 | G67: 1.5 | H67: =D67*F67*G67 | I67: =D67*'Сверка цен'!E67*G67 | J67: =D67*'Сверка цен'!F67*G67
A68: 61 | B68: Монтажник конструкций | C68: чел·мес | D68: 8 | E68: 2 × 4 | F68: ='Сверка цен'!G68 | G68: 1.5 | H68: =D68*F68*G68 | I68: =D68*'Сверка цен'!E68*G68 | J68: =D68*'Сверка цен'!F68*G68
A69: 62 | B69: Бетонщик | C69: чел·мес | D69: 8 | E69: 2 × 4 | F69: ='Сверка цен'!G69 | G69: 1.5 | H69: =D69*F69*G69 | I69: =D69*'Сверка цен'!E69*G69 | J69: =D69*'Сверка цен'!F69*G69
A70: 63 | B70: Штукатур-маляр (фасады) | C70: чел·мес | D70: 0 | E70: на бульваре фасадов нет | F70: ='Сверка цен'!G70 | G70: 1.5 | H70: =D70*F70*G70 | I70: =D70*'Сверка цен'!E70*G70 | J70: =D70*'Сверка цен'!F70*G70
A71: АРЕНДА ЖИЛЬЯ И ОФИСОВ
A72: 64 | B72: Квартира 1-комн., центр | C72: мес | D72: 4 | E72: нач. участка | F72: ='Сверка цен'!G72 | G72: 1 | H72: =D72*F72*G72 | I72: =D72*'Сверка цен'!E72*G72 | J72: =D72*'Сверка цен'!F72*G72
A73: 65 | B73: Офис ~20 м², центр (≈1350 ₽/м²) | C73: мес | D73: 4 | F73: ='Сверка цен'!G73 | G73: 1 | H73: =D73*F73*G73 | I73: =D73*'Сверка цен'!E73*G73 | J73: =D73*'Сверка цен'!F73*G73
A74: 66 | B74: Хостел, койко-место | C74: сутки | D74: 0 | E74: заменено общежитием | F74: ='Сверка цен'!G74 | G74: 1 | H74: =D74*F74*G74 | I74: =D74*'Сверка цен'!E74*G74 | J74: =D74*'Сверка цен'!F74*G74
A75: 66а | B75: Рабочее общежитие (в смете нет) | C75: чел·мес | D75: 80 | E75: 20 чел × 4 мес (приезжие) | F75: ='Сверка цен'!G75 | G75: 1 | H75: =D75*F75*G75 | I75: =D75*'Сверка цен'!E75*G75 | J75: =D75*'Сверка цен'!F75*G75
A76: 67 | B76: Гостиница 3*, стандарт | C76: сутки | D76: 30 | E76: командировки ИТР | F76: ='Сверка цен'!G76 | G76: 1 | H76: =D76*F76*G76 | I76: =D76*'Сверка цен'!E76*G76 | J76: =D76*'Сверка цен'!F76*G76
B78: Итого: ТРАНСПОРТ И СПЕЦТЕХНИКА | H78: =SUM(H3:H19) | I78: =SUM(I3:I19) | J78: =SUM(J3:J19)
B79: Итого: РАСХОДНЫЕ МАТЕРИАЛЫ | H79: =SUM(H21:H26) | I79: =SUM(I21:I26) | J79: =SUM(J21:J26)
B80: Итого: СТРОИТЕЛЬНЫЕ МАТЕРИАЛЫ | H80: =SUM(H28:H55) | I80: =SUM(I28:I55) | J80: =SUM(J28:J55)
B81: Итого: ЛОГИСТИКА МОСКВА → ХАБАРОВСК | H81: =SUM(H57:H58) | I81: =SUM(I57:I58) | J81: =SUM(J57:J58)
B82: Итого: ПЕРСОНАЛ | H82: =SUM(H60:H70) | I82: =SUM(I60:I70) | J82: =SUM(J60:J70)
B83: Итого: АРЕНДА ЖИЛЬЯ И ОФИСОВ | H83: =SUM(H72:H76) | I83: =SUM(I72:I76) | J83: =SUM(J72:J76)
B84: ИТОГО прямые затраты | H84: =H78+H79+H80+H81+H82+H83 | I84: =I78+I79+I80+I81+I82+I83 | J84: =J78+J79+J80+J81+J82+J83
B85: Непредвиденные 10% | H85: =H84*0.1 | I85: =I84*0.1 | J85: =J84*0.1
B86: ВСЕГО с непредвиденными | H86: =H84*1.1 | I86: =I84*1.1 | J86: =J84*1.1
B88: Сценарий: бульвар 500 × 20 м = 10 000 м², срок 4 месяца (~88 смен). Покрытия: гранитная брусчатка 2 500 м², асфальт 1 000 м² (5 см), резиновое покрытие 600 м² (10 мм), газон 5 000 м², освещение 1 000 м кабеля 5×16.
B89: Все объёмы — ДОПУЩЕНИЕ (в исходной смете количеств нет). Жёлтые ячейки — меняйте на объёмы из проекта/ВОР, суммы пересчитаются.
B90: Персонал умножен на 1,5 (НДФЛ 13% + страховые взносы 30% + травматизм ~0,9%). Районный коэфф. 1,2 и ДВ-надбавка обычно уже в цифре вакансии.
B91: Не учтены: проект, МАФ/скамейки/урны, светильники и опоры, саженцы, исполнительная документация, налоги подрядчика, сметная прибыль, НДС сверху там, где цена без НДС.

Sheet Риски и допущения
B1: ДОПУЩЕНИЯ
B2: В исходной смете нет количеств — итог посчитан по сценарию бульвара (лист «Сценарий»), объёмы условные.
B3: Каток 30 т в Хабаровске в аренду не найден — взяты грунтовые 16–20 т (поз. 15).
B4: Bobcat S630 — по аналогам S300/643/Барнаулец (поз. 4). Тягач 15 т — по тралам 30–65 т (поз. 8).
B5: Месячная аренда техники — расчёт 22 смены × ставка со скидкой 5–10%; прямых месячных предложений почти нет.
B6: Щебень фр. 80-120 у Корфовского карьера отсутствует — интерполяция между 40-70 и 100-200 (поз. 25).
B7: Асфальт — единственный публичный прайс АБЗ от 30.04.2025, индексирован на 2026 (+4–8%) (поз. 29).
B8: Бутовый камень — хабаровских цен нет, оценка по РФ + самосвал (поз. 35).
B9: Резиновая крошка, EPDM, связующее, пигменты — склады в центральной России, добавлена доставка ПЭК ~60 ₽/кг (поз. 37–40).
B10: Гранитная пиленая брусчатка 60 мм — в наличии в Хабаровске нет; цена РФ + ЖД-доставка отдельной строкой (поз. 46, 52). Альтернатива — местная колотая 2300–3400 ₽/м² или бетонная брусчатка.
B11: Цепное масло — федеральная розница (поз. 23). Пескобетон — аналог Старатели/RB, «Мастер Гарц» в Хабаровске нет (поз. 42).
B12: РИСКИ
... B24: Все цены собраны 20.10.2026 из открытых источников; ссылки — на листе «Сверка цен».
